movieapp/__init__.py
movieapp/cli.py
movieapp-0.1.2.dist-info/METADATA
movieapp-0.1.2.dist-info/WHEEL
movieapp-0.1.2.dist-info/entry_points.txt
movieapp-0.1.2.dist-info/RECORD
